Metadata-Version: 1.2
Name: android-stringslib
Version: 0.1.2
Summary: Android Strings Lib provides support for android's strings.xml files.  These files are used to translate strings in android apps.
Home-page: https://framagit.org/tyreunom/python-android-strings-lib
Author: Julien Lepiller
Author-email: julien@lepiller.eu
License: MIT
Keywords: android strings.xml translation
Platform: UNKNOWN
Classifier: Development Status :: 3 - Alpha
Classifier: Intended Audience :: Developers
Classifier: Topic :: Software Development :: Localization
Classifier: License :: OSI Approved :: MIT License
Classifier: Programming Language :: Python :: 3
Requires-Python: >=3
